aad_token_verify/__init__.py
aad_token_verify/exceptions.py
aad_token_verify/token_verifier.py
aad_token_verify-0.2.0.dist-info/LICENSE
aad_token_verify-0.2.0.dist-info/METADATA
aad_token_verify-0.2.0.dist-info/WHEEL
aad_token_verify-0.2.0.dist-info/top_level.txt
aad_token_verify-0.2.0.dist-info/RECORD
