Metadata-Version: 2.1
Name: aad-token-verify
Version: 0.2.0
Summary: A python utility library to verify an Azure Active Directory OAuth token
Home-page: https://github.com/GeneralMills/azure-ad-token-verify
Author: ['Daniel Thompson']
Author-email: daniel.thompson2@genmills.com 
License: MIT
Keywords: azure ad token oauth verify jwt
Classifier: Development Status :: 4 - Beta
Classifier: Intended Audience :: Developers
Classifier: Programming Language :: Python :: 3.6
Classifier: Programming Language :: Python :: 3.7
Classifier: Programming Language :: Python :: 3.8
Classifier: Programming Language :: Python :: 3.9
Classifier: License :: OSI Approved :: MIT License
Classifier: Topic :: Software Development :: Libraries :: Python Modules
Requires-Python: >=3.7
License-File: LICENSE
Requires-Dist: requests (<3,>=2.25.1)
Requires-Dist: PyJWT (<3,>=2.1.0)
Requires-Dist: cryptography (<42,>=41.0.1)
Requires-Dist: cachetools (<6,>=5.3.1)
